spdy/__init__.py
spdy/conn.py
spdy/dictionary.py
spdy/py.typed
spdy_py-0.2.0.dist-info/LICENSE
spdy_py-0.2.0.dist-info/METADATA
spdy_py-0.2.0.dist-info/WHEEL
spdy_py-0.2.0.dist-info/top_level.txt
spdy_py-0.2.0.dist-info/RECORD
