Metadata-Version: 2.1
Name: spdy-py
Version: 0.2.0
Summary: A pure Python implementation of the SDPY/3.x protocol
Home-page: https://github.com/mrodden/spdy-py
Author: Mathew Odden
Author-email: mrodden@us.ibm.com
License: LGPL
Platform: UNKNOWN
Classifier: Programming Language :: Python :: 3
Classifier: Programming Language :: Python :: 3.7
Classifier: Programming Language :: Python :: 3.8
Classifier: License :: OSI Approved :: GNU Library or Lesser General Public License (LGPL)
Requires-Python: >=3.6
License-File: LICENSE
